{
  "accentColor": "{{appsmith.theme.colors.primaryColor}}",
  "animateLoading": true,
  "borderRadius": "{{appsmith.theme.borderRadius.appBorderRadius}}",
  "bottomRow": 11,
  "boxShadow": "none",
  "closeOnSelection": true,
  "dateFormat": "YYYY-MM-DD",
  "datePickerType": "DATE_PICKER",
  "defaultDate": "{{JSDateTime.getToDate()}}",
  "dynamicBindingPathList": [
    {
      "key": "defaultDate"
    },
    {
      "key": "accentColor"
    },
    {
      "key": "borderRadius"
    }
  ],
  "dynamicHeight": "FIXED",
  "dynamicPropertyPathList": [
    {
      "key": "defaultDate"
    }
  ],
  "dynamicTriggerPathList": [
    {
      "key": "onDateSelected"
    }
  ],
  "firstDayOfWeek": 0,
  "isDisabled": false,
  "isLoading": false,
  "isRequired": false,
  "isVisible": true,
  "key": "zvm5w2f0x5",
  "label": "To",
  "labelAlignment": "left",
  "labelPosition": "Top",
  "labelTextSize": "0.875rem",
  "labelWidth": 5,
  "leftColumn": 11,
  "maxDate": "2121-12-31T18:29:00.000Z",
  "maxDynamicHeight": 9000,
  "minDate": "1920-12-31T18:30:00.000Z",
  "minDynamicHeight": 4,
  "minWidth": 450,
  "mobileBottomRow": 11,
  "mobileLeftColumn": 17,
  "mobileRightColumn": 37,
  "mobileTopRow": 4,
  "needsErrorInfo": false,
  "onDateSelected": "{{SelectQuery.run()}}",
  "originalBottomRow": 12,
  "originalTopRow": 5,
  "parentColumnSpace": 14.0078125,
  "parentId": "59rw5mx0bq",
  "parentRowSpace": 10,
  "renderMode": "CANVAS",
  "responsiveBehavior": "fill",
  "rightColumn": 20,
  "shortcuts": false,
  "timePrecision": "minute",
  "topRow": 4,
  "type": "DATE_PICKER_WIDGET2",
  "version": 2,
  "widgetId": "cyvxhgncde",
  "widgetName": "ToDatePicker"
}