{
  "gitSyncId": "6721c9c0fe37692ef010db3e_3f2b43d7-8372-43d8-9a67-c949e3f70797",
  "unpublishedPage": {
    "isHidden": true,
    "layouts": [
      {
        "dsl": {
          "backgroundColor": "none",
          "bottomRow": 840,
          "canExtend": true,
          "containerStyle": "none",
          "detachFromLayout": true,
          "dynamicBindingPathList": [],
          "leftColumn": 0,
          "minHeight": 870,
          "parentColumnSpace": 1,
          "parentRowSpace": 1,
          "rightColumn": 1224,
          "snapColumns": 64,
          "snapRows": 85,
          "topRow": 0,
          "type": "CANVAS_WIDGET",
          "version": 90,
          "widgetId": "0",
          "widgetName": "MainContainer"
        }
      }
    ],
    "name": "[Report] Project Efforts",
    "slug": "report-project-efforts"
  }
}