{
  "gitSyncId": "6721c9c0fe37692ef010db3e_55be83e8-53f4-439e-bfe3-a0682ab9956c",
  "id": "Member timesheet_InsertQuery",
  "pluginId": "postgres-plugin",
  "pluginType": "DB",
  "unpublishedAction": {
    "actionConfiguration": {
      "body": "INSERT INTO public.\"timesheet\" (\n\t\"note\",\n\t\"member_id\",\n\t\"project_id\",\n\t\"timesheet_type_id\",\n\t\"working_date\",\n\t\"estimated_hours\",\n\t\"actual_hours\",\n\t\"amount\",\n\t\"week_id\",\n\t\"is_support\")\nVALUES (\n\t'{{insert_form.formData.note}}',\n\t'{{insert_form.formData.member_id}}',\n\t'{{insert_form.formData.project_id}}',\n\t'{{insert_form.formData.timesheet_type_id}}',\n\t'{{insert_form.formData.working_date}}',\n\t'{{insert_form.formData.estimated_hours}}',\n\t'{{insert_form.formData.actual_hours}}',\n\t'{{insert_form.formData.amount}}',\n\t'{{insert_form.formData.week_id}}',\n\t'{{insert_form.formData.is_support || false}}');",
      "encodeParamsToggle": true,
      "paginationType": "NONE",
      "pluginSpecifiedTemplates": [
        {
          "value": true
        }
      ],
      "timeoutInMillisecond": 10000
    },
    "confirmBeforeExecute": false,
    "datasource": {
      "id": "TimesheetDB",
      "isAutoGenerated": false,
      "name": "TimesheetDB",
      "pluginId": "postgres-plugin"
    },
    "executeOnLoad": false,
    "name": "InsertQuery",
    "pageId": "Member timesheet",
    "userSetOnLoad": false
  }
}